README.rst
setup.py
joydivision/__init__.py
joydivision/scripts/__init__.py
joydivision/scripts/cli.py
rio_joydivision.egg-info/PKG-INFO
rio_joydivision.egg-info/SOURCES.txt
rio_joydivision.egg-info/dependency_links.txt
rio_joydivision.egg-info/entry_points.txt
rio_joydivision.egg-info/not-zip-safe
rio_joydivision.egg-info/requires.txt
rio_joydivision.egg-info/top_level.txt