Metadata-Version: 1.0
Name: rio-joydivision
Version: 0.0.1
Summary: Lines will tear us apart
Home-page: https://github.com/dnomadb/rio-joydivision
Author: Damon Burgett
Author-email: damon@mapbox.com
License: BSD
Platform: UNKNOWN
